[
  {
    "comment": "El mejor jugador del mundo",
    "session_id": "Como ser el GOAT",
    "tutor_id": "Cristiano Ronaldo",
    "reply": null,
    "date": "01/07/2025",
    "student_id": "Kevin Ramirez",
    "review_id": 107827,
    "replies": [
      {
        "comment": "Siiiuuuuuuu",
        "tutor_id": "Cristiano Ronaldo",
        "date": "01/07/2025"
      }
    ],
    "rating": 5
  },
  {
    "comment": "Bueno",
    "session_id": "Derecho02",
    "tutor_id": "Juan Jose Viquez Rios",
    "reply": null,
    "student_id": "Kevin Ramirez",
    "review_id": 17196,
    "date": "01/07/2025",
    "rating": 4
  },
  {
    "drive_link": "",
    "comment": "Manco",
    "reply": null,
    "tutor_id": "Cristiano Ronaldo",
    "session_id": "Como ser el GOAT",
    "date": "02/07/2025",
    "review_id": 17372,
    "student_id": "Prueba Est",
    "rating": 4
  },
  {
    "drive_link": "",
    "comment": "Hola",
    "session_id": "Límites",
    "tutor_id": "Ana Rodríguez",
    "reply": null,
    "student_id": "Prueba Est",
    "review_id": 25492,
    "date": "02/07/2025",
    "rating": 3
  },
  {
    "drive_link": "",
    "comment": "Mal ahí",
    "reply": null,
    "tutor_id": "Cristiano Ronaldo",
    "session_id": "Como ser el GOAT",
    "date": "02/07/2025",
    "review_id": 25869,
    "student_id": "Prueba Est",
    "rating": 1
  },
  {
    "drive_link": "https://drive.google.com/uc?id=1lvEDkcq-J_2eSZjfXkKi8dF6urK9NZYz",
    "comment": "No",
    "reply": null,
    "tutor_id": "Tutor Tutor",
    "session_id": "Lectura Crítica",
    "student_id": "EstudiantePrueba",
    "date": "01/07/2025",
    "review_id": 36133,
    "rating": 3
  },
  {
    "rating": 3,
    "comment": "Regular",
    "session_id": "Tutoria de Chill",
    "tutor_id": "Gabriel Serrano",
    "reply": null,
    "review_id": 48278,
    "student_id": "Prueba Est",
    "date": "02/07/2025",
    "drive_link": ""
  },
  {
    "drive_link": "",
    "comment": "Muy mala",
    "reply": null,
    "tutor_id": "Gabriel Serrano",
    "session_id": "Tutoria de Chill",
    "date": "02/07/2025",
    "review_id": 61366,
    "student_id": "Prueba Est",
    "rating": 1
  },
  {
    "drive_link": "",
    "comment": "Buena",
    "reply": null,
    "tutor_id": "Gabriel Serrano",
    "session_id": "Tutoria de Chill",
    "date": "02/07/2025",
    "review_id": 64361,
    "student_id": "Prueba Est",
    "rating": 5
  },
  {
    "drive_link": "",
    "comment": "a",
    "session_id": "Lectura Crítica",
    "tutor_id": "Pruebastudent",
    "reply": null,
    "student_id": "Prueba Est",
    "review_id": 74418,
    "date": "02/07/2025",
    "rating": 3
  },
  {
    "drive_link": "",
    "comment": "Regular",
    "session_id": "Tutoria de Chill",
    "tutor_id": "Gabriel Serrano",
    "reply": null,
    "date": "02/07/2025",
    "review_id": 82026,
    "student_id": "Prueba Est",
    "rating": 2
  },
  {
    "rating": 2,
    "comment": "a",
    "session_id": "Tutoria de Chill",
    "tutor_id": "Gabriel Serrano",
    "reply": null,
    "review_id": 87577,
    "student_id": "Prueba Est",
    "date": "02/07/2025",
    "drive_link": ""
  }
]